hmacauthenticator/__init__.py
jupyterhub_hmacauthenticator-1.0.dist-info/LICENSE
jupyterhub_hmacauthenticator-1.0.dist-info/METADATA
jupyterhub_hmacauthenticator-1.0.dist-info/WHEEL
jupyterhub_hmacauthenticator-1.0.dist-info/top_level.txt
jupyterhub_hmacauthenticator-1.0.dist-info/RECORD
