Metadata-Version: 2.1
Name: jupyterhub-hmacauthenticator
Version: 1.0
Summary: Dummy Authenticator for JupyterHub
Home-page: https://github.com/yuvipanda/jupyterhub-hmacauthenticator
Author: Yuvi Panda
Author-email: yuvipanda@gmail.com
License: 3 Clause BSD
Platform: UNKNOWN
Requires-Python: >=3.6
